file_downloader/__init__.py
file_downloader/cli.py
file_downloader/constants.py
dyp_file_downloader-0.3.0.dist-info/METADATA
dyp_file_downloader-0.3.0.dist-info/WHEEL
dyp_file_downloader-0.3.0.dist-info/entry_points.txt
dyp_file_downloader-0.3.0.dist-info/RECORD
