Metadata-Version: 2.4
Name: dyp_file_downloader
Version: 0.3.0
Summary: A CLI tool to download files based on file name flag
Project-URL: Homepage, https://github.com/yourusername/file_downloader
Project-URL: Bug Tracker, https://github.com/yourusername/file_downloader/issues
Author: Author
License-Expression: MIT
Keywords: cli,download,files
Classifier: Development Status :: 3 - Alpha
Classifier: Intended Audience :: Developers
Classifier: License :: OSI Approved :: MIT License
Classifier: Programming Language :: Python :: 3
Classifier: Programming Language :: Python :: 3.7
Classifier: Programming Language :: Python :: 3.8
Classifier: Programming Language :: Python :: 3.9
Classifier: Programming Language :: Python :: 3.10
Classifier: Programming Language :: Python :: 3.11
Requires-Python: >=3.7
Requires-Dist: click>=8.0.0
Requires-Dist: requests>=2.25.1
